mcfp/__init__.py
mcfp/collecter.py
mcfp/command/__init__.py
mcfp/command/commands.py
mcfp/command/execute.py
mcfp/command/util.py
mcfp/compiler.py
mcfp-0.1.2.dist-info/METADATA
mcfp-0.1.2.dist-info/WHEEL
mcfp-0.1.2.dist-info/RECORD
